odoo/addons/base_geoengine_demo/__init__.py
odoo/addons/base_geoengine_demo/__manifest__.py
odoo/addons/base_geoengine_demo/data/npa_geom.xml
odoo/addons/base_geoengine_demo/data/retail_machine_geom.xml
odoo/addons/base_geoengine_demo/i18n/base_geoengine_demo.pot
odoo/addons/base_geoengine_demo/images/map-hover.png
odoo/addons/base_geoengine_demo/images/map.png
odoo/addons/base_geoengine_demo/models/__init__.py
odoo/addons/base_geoengine_demo/models/geo_npa.py
odoo/addons/base_geoengine_demo/models/retail_machine.py
odoo/addons/base_geoengine_demo/security/ir.model.access.csv
odoo/addons/base_geoengine_demo/static/description/icon.png
odoo/addons/base_geoengine_demo/views/retail_machine.xml
odoo/addons/base_geoengine_demo/views/zip.xml
odoo11_addon_base_geoengine_demo-11.0.1.0.0.99.dev4.dist-info/METADATA
odoo11_addon_base_geoengine_demo-11.0.1.0.0.99.dev4.dist-info/RECORD
odoo11_addon_base_geoengine_demo-11.0.1.0.0.99.dev4.dist-info/WHEEL
odoo11_addon_base_geoengine_demo-11.0.1.0.0.99.dev4.dist-info/top_level.txt
